MANIFEST.in
README.md
pyproject.toml
setup.py
amuse_gadget2.egg-info/PKG-INFO
amuse_gadget2.egg-info/SOURCES.txt
amuse_gadget2.egg-info/dependency_links.txt
amuse_gadget2.egg-info/requires.txt
amuse_gadget2.egg-info/top_level.txt
src/amuse/community/gadget2/Makefile
src/amuse/community/gadget2/README
src/amuse/community/gadget2/__init__.py
src/amuse/community/gadget2/_version.py
src/amuse/community/gadget2/interface.cc
src/amuse/community/gadget2/interface.h
src/amuse/community/gadget2/interface.py
src/amuse/community/gadget2/makefile_options_nogravity
src/amuse/community/gadget2/makefile_options_normal
src/amuse/community/gadget2/makefile_options_periodic
src/amuse/community/gadget2/makefile_options_periodic_nogravity
src/amuse/community/gadget2/src/Doxyfile
src/amuse/community/gadget2/src/Makefile
src/amuse/community/gadget2/src/accel.c
src/amuse/community/gadget2/src/allocate.c
src/amuse/community/gadget2/src/allvars.c
src/amuse/community/gadget2/src/allvars.h
src/amuse/community/gadget2/src/begrun.c
src/amuse/community/gadget2/src/density.c
src/amuse/community/gadget2/src/density_at_pos.c
src/amuse/community/gadget2/src/domain.c
src/amuse/community/gadget2/src/driftfac.c
src/amuse/community/gadget2/src/endrun.c
src/amuse/community/gadget2/src/forcetree.c
src/amuse/community/gadget2/src/global.c
src/amuse/community/gadget2/src/gravtree.c
src/amuse/community/gadget2/src/gravtree_forcetest.c
src/amuse/community/gadget2/src/hydra.c
src/amuse/community/gadget2/src/init.c
src/amuse/community/gadget2/src/io.c
src/amuse/community/gadget2/src/longrange.c
src/amuse/community/gadget2/src/main.c
src/amuse/community/gadget2/src/makefile_options
src/amuse/community/gadget2/src/ngb.c
src/amuse/community/gadget2/src/peano.c
src/amuse/community/gadget2/src/pm_nonperiodic.c
src/amuse/community/gadget2/src/pm_periodic.c
src/amuse/community/gadget2/src/potential.c
src/amuse/community/gadget2/src/predict.c
src/amuse/community/gadget2/src/proto.h
src/amuse/community/gadget2/src/read_ic.c
src/amuse/community/gadget2/src/restart.c
src/amuse/community/gadget2/src/run.c
src/amuse/community/gadget2/src/sigvel.c
src/amuse/community/gadget2/src/system.c
